ordeq_duckdb/__init__.py
ordeq_duckdb/_version.py
ordeq_duckdb/connection.py
ordeq_duckdb/csv.py
ordeq_duckdb/parquet.py
ordeq_duckdb/py.typed
ordeq_duckdb/table.py
ordeq_duckdb/view.py
ordeq_duckdb-1.0.2.dist-info/licenses/LICENSE
ordeq_duckdb-1.0.2.dist-info/METADATA
ordeq_duckdb-1.0.2.dist-info/WHEEL
ordeq_duckdb-1.0.2.dist-info/top_level.txt
ordeq_duckdb-1.0.2.dist-info/RECORD
