Metadata-Version: 2.4
Name: ordeq_duckdb
Version: 1.0.2
Summary: DuckDB integration for Ordeq
Author: Niels Neerhoff, Simon Brugman
Maintainer: Niels Neerhoff, Simon Brugman
License-Expression: MIT
Requires-Python: >=3.10
License-File: LICENSE
Requires-Dist: ordeq>=1.4.0
Requires-Dist: duckdb
Dynamic: license-file
